main.py
mcp_weather_full-1.0.1.dist-info/METADATA
mcp_weather_full-1.0.1.dist-info/WHEEL
mcp_weather_full-1.0.1.dist-info/entry_points.txt
mcp_weather_full-1.0.1.dist-info/top_level.txt
mcp_weather_full-1.0.1.dist-info/RECORD
