Metadata-Version: 2.4
Name: mcp-weather-full
Version: 1.0.1
Summary: MCP test for weather
Requires-Python: >=3.10
Requires-Dist: httpx>=0.28.1
Requires-Dist: mcp>=1.12.2
